CHANGELOG.md
anonlinkclient/__init__.py
anonlinkclient/cli.py
anonlinkclient/data/blocking_schema.json
anonlinkclient/data/nvtr_schema.json
anonlinkclient/data/randomnames-schema.json
anonlinkclient/data/schema.json
anonlinkclient/utils.py
anonlink_client-0.1.9.dist-info/LICENSE
anonlink_client-0.1.9.dist-info/METADATA
anonlink_client-0.1.9.dist-info/WHEEL
anonlink_client-0.1.9.dist-info/entry_points.txt
anonlink_client-0.1.9.dist-info/RECORD
