Metadata-Version: 2.1
Name: anonlink-client
Version: 0.1.9
Summary: Client side tool for clkhash and blocklib
Home-page: https://github.com/data61/anonlink-client
License: Apache-2.0
Author: Wilko Henecka
Author-email: wilkohenecka@gmx.net
Requires-Python: >=3.8,<3.12
Classifier: Development Status :: 5 - Production/Stable
Classifier: Environment :: Console
Classifier: License :: OSI Approved :: Apache Software License
Classifier: Natural Language :: English
Classifier: Operating System :: OS Independent
Classifier: Programming Language :: Python :: 3
Classifier: Programming Language :: Python :: 3.8
Classifier: Programming Language :: Python :: 3.9
Classifier: Programming Language :: Python :: 3.10
Classifier: Programming Language :: Python :: 3.11
Classifier: Programming Language :: Python :: 3.10
Classifier: Programming Language :: Python :: 3.11
Classifier: Programming Language :: Python :: 3.7
Classifier: Programming Language :: Python :: 3.8
Classifier: Programming Language :: Python :: 3.9
Classifier: Programming Language :: Python :: Implementation :: CPython
Classifier: Programming Language :: Python :: Implementation :: PyPy
Classifier: Topic :: Security :: Cryptography
Requires-Dist: anonlink (>=0.15.2,<0.16.0)
Requires-Dist: bashplotlib (>=0.6,<0.7)
Requires-Dist: blocklib (>=0.1.8,<0.2.0)
Requires-Dist: click (>=7.1.2,<9.0.0)
Requires-Dist: clkhash (>=0.18.0,<0.19.0)
Requires-Dist: ijson (>=3.1.4,<4.0.0)
Requires-Dist: jsonschema (>=3.2,<5.0)
Requires-Dist: jupyter (>=1.0.0,<2.0.0)
Requires-Dist: minio (>=7.0.3,<8.0.0)
Requires-Dist: pydantic (>=1.10.5,<2.0.0)
Requires-Dist: requests (>=2.25.1,<3.0.0)
Requires-Dist: retrying (>=1.3.3,<2.0.0)
Project-URL: Bug Tracker, https://github.com/data61/anonlink-client/issues
Project-URL: Documentation, https://anonlink-client.readthedocs.io/en/latest/
Project-URL: Repository, https://github.com/data61/anonlink-client
